[{"model": "api.LectureRoom", "pk": 1, "fields": {"lecture_room": "総合教育２号館E10示範教室（対面と遠隔（オンデマンドと双方向）の併用）"}}, {"model": "api.LectureRoom", "pk": 2, "fields": {"lecture_room": "総合教育講義棟B9講義室（対面のみ）"}}, {"model": "api.LectureRoom", "pk": 3, "fields": {"lecture_room": "総合教育講義棟B1講義室（対面と遠隔（オンデマンド）の併用）"}}, {"model": "api.LectureRoom", "pk": 4, "fields": {"lecture_room": "総合教育講義棟D1講義室（対面と遠隔（オンデマンドと双方向）の併用）"}}, {"model": "api.LectureRoom", "pk": 5, "fields": {"lecture_room": "総合教育２号館Ｄ13演習室（対面のみ）"}}, {"model": "api.LectureRoom", "pk": 6, "fields": {"lecture_room": "総合教育講義棟B7講義室（対面と遠隔（オンデマンド）の併用）"}}, {"model": "api.LectureRoom", "pk": 7, "fields": {"lecture_room": "（対面と遠隔（オンデマンドと双方向）の併用）"}}, {"model": "api.LectureRoom", "pk": 8, "fields": {"lecture_room": "医学類教育棟第1講義室（対面と遠隔（オンデマンドと双方向）の併用）"}}, {"model": "api.LectureRoom", "pk": 9, "fields": {"lecture_room": "総合教育２号館B10示範教室（対面と遠隔（オンデマンド）の併用）"}}, {"model": "api.LectureRoom", "pk": 10, "fields": {"lecture_room": "総合教育講義棟D3講義室（対面と遠隔（オンデマンドと双方向）の併用）"}}, {"model": "api.LectureRoom", "pk": 11, "fields": {"lecture_room": "人間社会第１講義棟303講義室（対面と遠隔（双方向）の併用）"}}, {"model": "api.LectureRoom", "pk": 12, "fields": {"lecture_room": "学術メディア創成センター演習室（対面と遠隔（双方向）の併用）"}}, {"model": "api.LectureRoom", "pk": 13, "fields": {"lecture_room": "総合教育講義棟C6講義室（対面のみ）"}}, {"model": "api.LectureRoom", "pk": 14, "fields": {"lecture_room": "総合教育講義棟A3講義室（対面のみ）"}}, {"model": "api.LectureRoom", "pk": 15, "fields": {"lecture_room": "総合教育講義棟C1講義室（対面と遠隔（オンデマンドと双方向）の併用）"}}, {"model": "api.LectureRoom", "pk": 16, "fields": {"lecture_room": "総合教育講義棟D1講義室（対面と遠隔（オンデマンド）の併用）"}}, {"model": "api.LectureRoom", "pk": 17, "fields": {"lecture_room": "学術メディア創成センター多目的教室（対面のみ）"}}, {"model": "api.LectureRoom", "pk": 18, "fields": {"lecture_room": "総合教育２号館C10示範教室（対面と遠隔（双方向）の併用）"}}, {"model": "api.LectureRoom", "pk": 19, "fields": {"lecture_room": "総合教育２号館C10示範教室（対面のみ）"}}, {"model": "api.LectureRoom", "pk": 20, "fields": {"lecture_room": "総合教育講義棟D9講義室（対面のみ）"}}, {"model": "api.LectureRoom", "pk": 21, "fields": {"lecture_room": "総合教育講義棟C8講義室（対面と遠隔（オンデマンド）の併用）"}}, {"model": "api.LectureRoom", "pk": 22, "fields": {"lecture_room": "人間社会第１講義棟303講義室（対面のみ）"}}, {"model": "api.LectureRoom", "pk": 23, "fields": {"lecture_room": "総合教育講義棟B5講義室（対面と遠隔（オンデマンドと双方向）の併用）"}}, {"model": "api.LectureRoom", "pk": 24, "fields": {"lecture_room": "総合教育講義棟C1講義室（対面と遠隔（オンデマンド）の併用）"}}, {"model": "api.LectureRoom", "pk": 25, "fields": {"lecture_room": "総合教育講義棟D6講義室（対面と遠隔（オンデマンドと双方向）の併用）"}}, {"model": "api.LectureRoom", "pk": 26, "fields": {"lecture_room": "自然科学本館（総合研究棟Ⅳ）203講義室（対面のみ）"}}, {"model": "api.LectureRoom", "pk": 27, "fields": {"lecture_room": "総合教育２号館B10示範教室（対面のみ）"}}, {"model": "api.LectureRoom", "pk": 28, "fields": {"lecture_room": "（遠隔（双方向）のみ）"}}, {"model": "api.LectureRoom", "pk": 29, "fields": {"lecture_room": "総合教育講義棟B5講義室（対面と遠隔（オンデマンド）の併用）"}}, {"model": "api.LectureRoom", "pk": 30, "fields": {"lecture_room": "総合教育２号館E10示範教室（対面のみ）"}}, {"model": "api.LectureRoom", "pk": 31, "fields": {"lecture_room": "総合教育講義棟D4講義室(AV教室)（対面のみ）"}}, {"model": "api.LectureRoom", "pk": 32, "fields": {"lecture_room": "総合教育講義棟C4講義室（対面のみ）"}}, {"model": "api.LectureRoom", "pk": 33, "fields": {"lecture_room": "総合教育講義棟C4講義室（対面と遠隔（オンデマンド）の併用）"}}, {"model": "api.LectureRoom", "pk": 34, "fields": {"lecture_room": "人間社会第２講義棟202講義室（対面のみ）"}}, {"model": "api.LectureRoom", "pk": 35, "fields": {"lecture_room": "人間社会第２講義棟207講義室（対面のみ）"}}, {"model": "api.LectureRoom", "pk": 36, "fields": {"lecture_room": "人間社会第１講義棟302講義室（対面と遠隔（オンデマンド）の併用）"}}, {"model": "api.LectureRoom", "pk": 37, "fields": {"lecture_room": "自然科学本館（総合研究棟Ⅳ）101講義室（対面のみ）"}}, {"model": "api.LectureRoom", "pk": 38, "fields": {"lecture_room": "総合教育講義棟C8講義室（対面と遠隔（オンデマンドと双方向）の併用）"}}, {"model": "api.LectureRoom", "pk": 39, "fields": {"lecture_room": "総合教育２号館Ｃ14演習室（対面のみ）"}}, {"model": "api.LectureRoom", "pk": 40, "fields": {"lecture_room": "総合教育講義棟C5講義室（対面のみ）"}}, {"model": "api.LectureRoom", "pk": 41, "fields": {"lecture_room": "総合教育２号館Ｄ14遠隔授業講義室（対面のみ）"}}, {"model": "api.LectureRoom", "pk": 42, "fields": {"lecture_room": "総合教育講義棟B4講義室（対面と遠隔（双方向）の併用）"}}, {"model": "api.LectureRoom", "pk": 43, "fields": {"lecture_room": "総合教育２号館C10示範教室（対面と遠隔（オンデマンド）の併用）"}}, {"model": "api.LectureRoom", "pk": 44, "fields": {"lecture_room": "人間社会４号館音楽ﾎｰﾙ（対面のみ）"}}, {"model": "api.LectureRoom", "pk": 45, "fields": {"lecture_room": "総合教育講義棟D2講義室（対面と遠隔（オンデマンドと双方向）の併用）"}}, {"model": "api.LectureRoom", "pk": 46, "fields": {"lecture_room": "総合教育講義棟D2講義室（対面のみ）"}}, {"model": "api.LectureRoom", "pk": 47, "fields": {"lecture_room": "総合教育講義棟C2講義室（対面のみ）"}}, {"model": "api.LectureRoom", "pk": 48, "fields": {"lecture_room": "総合教育講義棟A1講義室（対面と遠隔（オンデマンドと双方向）の併用）"}}, {"model": "api.LectureRoom", "pk": 49, "fields": {"lecture_room": "総合教育講義棟A1講義室（対面と遠隔（オンデマンド）の併用）"}}, {"model": "api.LectureRoom", "pk": 50, "fields": {"lecture_room": "人間社会第２講義棟201講義室（対面のみ）"}}, {"model": "api.LectureRoom", "pk": 51, "fields": {"lecture_room": "総合教育講義棟B1講義室（対面と遠隔（オンデマンドと双方向）の併用）"}}, {"model": "api.LectureRoom", "pk": 52, "fields": {"lecture_room": "総合教育講義棟C2講義室（ハイフレックス授業型HyFlexType）"}}, {"model": "api.LectureRoom", "pk": 53, "fields": {"lecture_room": "総合教育講義棟C5講義室（対面と遠隔（オンデマンド）の併用）"}}, {"model": "api.LectureRoom", "pk": 54, "fields": {"lecture_room": "総合教育講義棟B7講義室（対面のみ）"}}, {"model": "api.LectureRoom", "pk": 55, "fields": {"lecture_room": "人間社会第２講義棟401講義室（対面のみ）"}}, {"model": "api.LectureRoom", "pk": 56, "fields": {"lecture_room": "総合教育講義棟C3講義室（対面のみ）"}}, {"model": "api.LectureRoom", "pk": 57, "fields": {"lecture_room": "総合教育講義棟D7講義室（対面のみ）"}}, {"model": "api.LectureRoom", "pk": 58, "fields": {"lecture_room": "総合教育講義棟D6講義室（対面と遠隔（オンデマンド）の併用）"}}, {"model": "api.LectureRoom", "pk": 59, "fields": {"lecture_room": "総合教育講義棟C8講義室（対面のみ）"}}, {"model": "api.LectureRoom", "pk": 60, "fields": {"lecture_room": "総合教育講義棟B3講義室（対面のみ）"}}, {"model": "api.LectureRoom", "pk": 61, "fields": {"lecture_room": "総合教育講義棟B1講義室（対面のみ）"}}, {"model": "api.LectureRoom", "pk": 62, "fields": {"lecture_room": "総合教育講義棟C6講義室（基本的に対面で，または対面と双方向の併用で講義を行います．）"}}, {"model": "api.LectureRoom", "pk": 63, "fields": {"lecture_room": "総合教育講義棟B8講義室（対面と遠隔（オンデマンド）の併用）"}}, {"model": "api.LectureRoom", "pk": 64, "fields": {"lecture_room": "総合教育講義棟A1講義室（対面と遠隔（双方向）の併用）"}}, {"model": "api.LectureRoom", "pk": 65, "fields": {"lecture_room": "総合教育講義棟C6講義室（第1回目の講義はオンデマンド型．それ以降は，基本的に対面型または併用型）"}}, {"model": "api.LectureRoom", "pk": 66, "fields": {"lecture_room": "総合教育２号館E15講義室（対面のみ）"}}, {"model": "api.LectureRoom", "pk": 67, "fields": {"lecture_room": "総合教育講義棟B4講義室（対面と遠隔（オンデマンドと双方向）の併用）"}}, {"model": "api.LectureRoom", "pk": 68, "fields": {"lecture_room": "総合教育講義棟B4講義室（対面と遠隔（オンデマンド）の併用）"}}, {"model": "api.LectureRoom", "pk": 69, "fields": {"lecture_room": "総合教育２号館B10示範教室（ハイフレックス授業型HyFlexType）"}}, {"model": "api.LectureRoom", "pk": 70, "fields": {"lecture_room": "総合教育講義棟B2講義室（対面のみ）"}}, {"model": "api.LectureRoom", "pk": 71, "fields": {"lecture_room": "総合教育講義棟B2講義室（対面と遠隔（オンデマンドと双方向）の併用）"}}, {"model": "api.LectureRoom", "pk": 72, "fields": {"lecture_room": "総合教育講義棟C11演習室（対面のみ）"}}, {"model": "api.LectureRoom", "pk": 73, "fields": {"lecture_room": "人間社会第１講義棟302講義室（対面と遠隔（オンデマンドと双方向）の併用）"}}, {"model": "api.LectureRoom", "pk": 74, "fields": {"lecture_room": "人間社会第２講義棟406講義室（対面のみ）"}}, {"model": "api.LectureRoom", "pk": 75, "fields": {"lecture_room": "自然科学５号館Ｂ大講義室（対面と遠隔（オンデマンドと双方向）の併用）"}}, {"model": "api.LectureRoom", "pk": 76, "fields": {"lecture_room": "総合教育講義棟D1講義室（対面のみ）"}}, {"model": "api.LectureRoom", "pk": 77, "fields": {"lecture_room": "総合教育講義棟A1講義室（対面のみ）"}}, {"model": "api.LectureRoom", "pk": 78, "fields": {"lecture_room": "総合教育講義棟B6講義室（対面のみ）"}}, {"model": "api.LectureRoom", "pk": 79, "fields": {"lecture_room": "人間社会第１講義棟303講義室（対面と遠隔（オンデマンドと双方向）の併用）"}}, {"model": "api.LectureRoom", "pk": 80, "fields": {"lecture_room": "総合教育１号館E１講義室（対面のみ）"}}, {"model": "api.LectureRoom", "pk": 81, "fields": {"lecture_room": "総合教育２号館F10講義室（対面と遠隔（オンデマンド）の併用）"}}, {"model": "api.LectureRoom", "pk": 82, "fields": {"lecture_room": "総合教育講義棟B6講義室（対面と遠隔（オンデマンドと双方向）の併用）"}}, {"model": "api.LectureRoom", "pk": 83, "fields": {"lecture_room": "総合教育講義棟A4講義室（対面のみ）"}}, {"model": "api.LectureRoom", "pk": 84, "fields": {"lecture_room": "総合教育講義棟D7講義室（対面と遠隔（オンデマンド）の併用）"}}, {"model": "api.LectureRoom", "pk": 85, "fields": {"lecture_room": "（遠隔（オンデマンド）のみ）"}}, {"model": "api.LectureRoom", "pk": 86, "fields": {"lecture_room": "（対面と遠隔（オンデマンド）の併用）"}}, {"model": "api.LectureRoom", "pk": 87, "fields": {"lecture_room": "総合教育講義棟Ｄ５講義室（対面と遠隔（オンデマンドと双方向）の併用）"}}, {"model": "api.LectureRoom", "pk": 88, "fields": {"lecture_room": "総合教育講義棟B3講義室（対面と遠隔（オンデマンド）の併用）"}}, {"model": "api.LectureRoom", "pk": 89, "fields": {"lecture_room": "総合教育２号館生物学学生実験室（対面のみ）"}}, {"model": "api.LectureRoom", "pk": 90, "fields": {"lecture_room": "自然科学２号館（総合研究棟Ⅱ）自然システム地球学実験室2（対面のみ）"}}, {"model": "api.LectureRoom", "pk": 91, "fields": {"lecture_room": "人間社会第１講義棟101講義室（対面のみ）"}}, {"model": "api.LectureRoom", "pk": 92, "fields": {"lecture_room": "総合教育講義棟Ｄ５講義室（対面のみ）"}}, {"model": "api.LectureRoom", "pk": 93, "fields": {"lecture_room": "総合教育講義棟D3講義室（対面のみ）"}}, {"model": "api.LectureRoom", "pk": 94, "fields": {"lecture_room": "総合教育講義棟C7講義室（対面のみ）"}}, {"model": "api.LectureRoom", "pk": 95, "fields": {"lecture_room": "総合教育２号館D10講義室（対面のみ）"}}, {"model": "api.LectureRoom", "pk": 96, "fields": {"lecture_room": "総合教育講義棟D6講義室（対面のみ）"}}, {"model": "api.LectureRoom", "pk": 97, "fields": {"lecture_room": "自然科学５号館Ｂ第２講義室（対面のみ）"}}, {"model": "api.LectureRoom", "pk": 98, "fields": {"lecture_room": "総合教育講義棟C4講義室（対面と遠隔（オンデマンドと双方向）の併用）"}}, {"model": "api.LectureRoom", "pk": 99, "fields": {"lecture_room": "総合教育２号館物理学学生実験室（対面と遠隔（オンデマンドと双方向）の併用）"}}, {"model": "api.LectureRoom", "pk": 100, "fields": {"lecture_room": "総合教育講義棟C3講義室（対面と遠隔（双方向）の併用）"}}, {"model": "api.LectureRoom", "pk": 101, "fields": {"lecture_room": "総合教育講義棟B4講義室（対面のみ）"}}, {"model": "api.LectureRoom", "pk": 102, "fields": {"lecture_room": "人間社会第１講義棟304演習室（対面のみ）"}}, {"model": "api.LectureRoom", "pk": 103, "fields": {"lecture_room": "総合教育講義棟C2講義室（対面と遠隔（オンデマンドと双方向）の併用）"}}, {"model": "api.LectureRoom", "pk": 104, "fields": {"lecture_room": "総合教育講義棟D8講義室（対面と遠隔（オンデマンドと双方向）の併用）"}}, {"model": "api.LectureRoom", "pk": 105, "fields": {"lecture_room": "自然科学本館（総合研究棟Ⅳ）205講義室（対面のみ）"}}, {"model": "api.LectureRoom", "pk": 106, "fields": {"lecture_room": "総合教育講義棟D4講義室(AV教室)（対面と遠隔（オンデマンドと双方向）の併用）"}}, {"model": "api.LectureRoom", "pk": 107, "fields": {"lecture_room": "総合教育２号館D10講義室（対面と遠隔（オンデマンド）の併用）"}}, {"model": "api.LectureRoom", "pk": 108, "fields": {"lecture_room": "総合教育講義棟C9講義室（対面のみ）"}}, {"model": "api.LectureRoom", "pk": 109, "fields": {"lecture_room": "総合教育講義棟C5講義室（対面と遠隔（オンデマンドと双方向）の併用）"}}, {"model": "api.LectureRoom", "pk": 110, "fields": {"lecture_room": "人間社会第１講義棟301講義室（対面のみ）"}}, {"model": "api.LectureRoom", "pk": 111, "fields": {"lecture_room": "総合教育講義棟B11演習室（対面のみ）"}}, {"model": "api.LectureRoom", "pk": 112, "fields": {"lecture_room": "総合教育講義棟C1講義室（対面のみ）"}}, {"model": "api.LectureRoom", "pk": 113, "fields": {"lecture_room": "総合教育講義棟B5講義室（対面のみ）"}}, {"model": "api.LectureRoom", "pk": 114, "fields": {"lecture_room": "総合教育講義棟C2講義室（対面と遠隔（オンデマンド）の併用）"}}, {"model": "api.LectureRoom", "pk": 115, "fields": {"lecture_room": "総合教育講義棟B9講義室（対面と遠隔（オンデマンド）の併用）"}}, {"model": "api.LectureRoom", "pk": 116, "fields": {"lecture_room": "総合教育講義棟D8講義室（対面のみ）"}}, {"model": "api.LectureRoom", "pk": 117, "fields": {"lecture_room": "自然科学５号館Ｂ大講義室（対面のみ）"}}, {"model": "api.LectureRoom", "pk": 118, "fields": {"lecture_room": "十全講堂十全講堂（対面と遠隔（オンデマンドと双方向）の併用）"}}, {"model": "api.LectureRoom", "pk": 119, "fields": {"lecture_room": "人間社会第１講義棟311演習室（対面と遠隔（オンデマンドと双方向）の併用）"}}, {"model": "api.LectureRoom", "pk": 120, "fields": {"lecture_room": "総合教育講義棟C6講義室（対面と遠隔（オンデマンド）の併用）"}}, {"model": "api.LectureRoom", "pk": 121, "fields": {"lecture_room": "総合教育講義棟B2講義室（対面と遠隔（オンデマンド）の併用）"}}, {"model": "api.LectureRoom", "pk": 122, "fields": {"lecture_room": "（個人の海外渡航やオンライン留学を対象としており、授業は行わない）"}}, {"model": "api.LectureRoom", "pk": 123, "fields": {"lecture_room": "保健学類３号館電気･物理系共通実験･実習室（対面と遠隔（オンデマンド）の併用）"}}, {"model": "api.LectureRoom", "pk": 124, "fields": {"lecture_room": "総合教育講義棟B11演習室（対面と遠隔（双方向）の併用）"}}, {"model": "api.LectureRoom", "pk": 125, "fields": {"lecture_room": "総合教育講義棟B7講義室（対面と遠隔（オンデマンドと双方向）の併用）"}}, {"model": "api.LectureRoom", "pk": 126, "fields": {"lecture_room": "総合教育講義棟D4講義室(AV教室)（対面と遠隔（オンデマンド）の併用）"}}, {"model": "api.LectureRoom", "pk": 127, "fields": {"lecture_room": "自然科学系図書館・南福利施設AVﾎｰﾙ（対面のみ）"}}, {"model": "api.LectureRoom", "pk": 128, "fields": {"lecture_room": "（対面のみ）"}}, {"model": "api.LectureRoom", "pk": 129, "fields": {"lecture_room": "（海外での異文化体験を対象とした科目であるため上記に該当せず）"}}, {"model": "api.LectureRoom", "pk": 130, "fields": {"lecture_room": "総合教育２号館化学学生実験室（対面のみ）"}}, {"model": "api.LectureRoom", "pk": 131, "fields": {"lecture_room": "総合教育講義棟C3講義室（対面と遠隔（オンデマンドと双方向）の併用）"}}, {"model": "api.LectureRoom", "pk": 132, "fields": {"lecture_room": "総合教育１号館Ａ５演習室（対面のみ）"}}, {"model": "api.LectureRoom", "pk": 133, "fields": {"lecture_room": "総合教育講義棟C4講義室（対面と遠隔（双方向）の併用）"}}, {"model": "api.LectureRoom", "pk": 134, "fields": {"lecture_room": "総合教育２号館地学学生実験室（対面のみ）"}}, {"model": "api.LectureRoom", "pk": 135, "fields": {"lecture_room": "総合教育２号館物理学学生実験室（対面のみ）"}}, {"model": "api.LectureRoom", "pk": 136, "fields": {"lecture_room": "総合教育講義棟Ｄ５講義室（対面と遠隔（オンデマンド）の併用）"}}, {"model": "api.LectureRoom", "pk": 137, "fields": {"lecture_room": "総合教育２号館B10示範教室（対面と遠隔（オンデマンドと双方向）の併用）"}}, {"model": "api.LectureRoom", "pk": 138, "fields": {"lecture_room": "総合教育２号館C10示範教室（対面と遠隔（オンデマンドと双方向）の併用）"}}, {"model": "api.LectureRoom", "pk": 139, "fields": {"lecture_room": "人間社会３号館調理学実験室（対面のみ）"}}, {"model": "api.LectureRoom", "pk": 140, "fields": {"lecture_room": "人間社会第２講義棟301講義室（対面と遠隔（オンデマンドと双方向）の併用）"}}, {"model": "api.LectureRoom", "pk": 141, "fields": {"lecture_room": "総合教育講義棟A2講義室（対面のみ）"}}, {"model": "api.LectureRoom", "pk": 142, "fields": {"lecture_room": "総合教育講義棟B5講義室（対面と遠隔（双方向）の併用）"}}, {"model": "api.LectureRoom", "pk": 143, "fields": {"lecture_room": "総合教育２号館D10講義室（対面と遠隔（オンデマンドと双方向）の併用）"}}, {"model": "api.LectureRoom", "pk": 144, "fields": {"lecture_room": "総合教育講義棟B8講義室（対面のみ）"}}, {"model": "api.LectureRoom", "pk": 145, "fields": {"lecture_room": "総合教育講義棟C3講義室（対面と遠隔（オンデマンド）の併用）"}}, {"model": "api.LectureRoom", "pk": 146, "fields": {"lecture_room": "（対面と遠隔（双方向）の併用）"}}, {"model": "api.LectureRoom", "pk": 147, "fields": {"lecture_room": "総合教育２号館F10講義室（対面のみ）"}}]